{
  "required": true,
  "minVersion": "0.8",
  "package": "cursedbread.morefeatures.mixin",
  "compatibilityLevel": "JAVA_8",
  "mixins": [
    "blockmixins.NetherrackCrushingMixin",
    "blockmixins.superores.OreToSuperoreCoal",
    "blockmixins.superores.OreToSuperoreDiamond",
    "blockmixins.superores.OreToSuperoreGold",
    "blockmixins.superores.OreToSuperoreIron",
    "blockmixins.superores.OreToSuperoreLapis",
    "blockmixins.superores.OreToSuperoreNetherCoal",
    "blockmixins.superores.OreToSuperoreRedstone",
    "entitymixins.EntityBagRender",
    "entitymixins.SoulDrop",
    "generationmixins.BigBirchTressMixin",
    "generationmixins.BlockGrassMixin",
    "generationmixins.BurningLogMixin",
    "generationmixins.ChunkDecoratorOverworldMixin",
    "generationmixins.ColoredGlowstoneAMixin",
    "generationmixins.ColoredGlowstoneBMixin",
    "generationmixins.LabyrinthGenerationMixin",
    "generationmixins.NewBlockGeneratorMixin",
    "generationmixins.nether.ChunkDecoratorNetherMixin",
    "itemsmixins.BagArmor",
    "itemsmixins.ClimbingPickaxeMixin",
    "itemsmixins.ContainerWorkbenchMixin",
    "itemsmixins.ItemCannonMixin",
    "itemsmixins.SlotArmorMixin",
    "itemsmixins.SpawnerSurvival",
    "itemsmixins.WorkbenchFix",
    "itemsmixins.fuels.FurnanceBlastFuelMixin",
    "itemsmixins.fuels.FurnanceFuelMixin"
  ],
  "client": [
    "entitymixins.EntityPlayerMixin"
  ],
  "injectors": {
    "defaultRequire": 1
  }
}
